Metadata-Version: 2.1
Name: youqu-html
Version: 2024.6.19
Summary: youqu-html
Author-email: mikigo <huangmingqiang@uniontech.com>
License: GPL2.0
License-File: LICENSE
Requires-Python: >=3.7
